plone.recipe.varnish-6.0.13.1-py3.11-nspkg.pth
plone/recipe/varnish/__init__.py
plone/recipe/varnish/recipe.py
plone/recipe/varnish/vclgen.py
plone/recipe/varnish/templates/oldsnippets.txt
plone/recipe/varnish/templates/start_script.jinja2
plone/recipe/varnish/templates/varnish6.vcl.jinja2
plone/recipe/varnish/tests/__init__.py
plone/recipe/varnish/tests/recipe.rst
plone/recipe/varnish/tests/test_recipe.py
plone/recipe/varnish/tests/test_vclgen.py
plone/recipe/varnish/tests/vclgen.rst
plone.recipe.varnish-6.0.13.1.dist-info/METADATA
plone.recipe.varnish-6.0.13.1.dist-info/WHEEL
plone.recipe.varnish-6.0.13.1.dist-info/entry_points.txt
plone.recipe.varnish-6.0.13.1.dist-info/namespace_packages.txt
plone.recipe.varnish-6.0.13.1.dist-info/top_level.txt
plone.recipe.varnish-6.0.13.1.dist-info/RECORD
