Metadata-Version: 2.1
Name: plone.recipe.varnish
Version: 6.0.13.1
Summary: Build and/or configure Varnish Cache with zc.buildout
Home-page: https://pypi.python.org/pypi/plone.recipe.varnish
Author: Wichert Akkerman, et al
Author-email: wichert@wiggy.net
License: BSD
Keywords: buildout varnish cache proxy
Classifier: Framework :: Buildout
Classifier: Framework :: Zope2
Classifier: Intended Audience :: System Administrators
Classifier: License :: OSI Approved :: BSD License
Classifier: Operating System :: POSIX
Classifier: Programming Language :: Python
Classifier: Programming Language :: Python :: 2.7
Classifier: Programming Language :: Python :: 3.6
Classifier: Programming Language :: Python :: 3.7
Classifier: Programming Language :: Python :: 3.8
Classifier: Topic :: Internet :: Proxy Servers
Classifier: Development Status :: 5 - Production/Stable
Requires-Python: >=2.7,!=3.0.*,!=3.1.*,!=3.2.*,!=3.3.*,!=3.4.*
Requires-Dist: jinja2 >=2.7.3
Requires-Dist: setuptools
Requires-Dist: zc.buildout
Requires-Dist: zc.recipe.cmmi
Requires-Dist: jinja2 <3 ; python_version < "3"
Requires-Dist: MarkupSafe <2 ; python_version < "3"
Provides-Extra: test
Requires-Dist: interlude ; extra == 'test'
